preflibtools/__init__.py
preflibtools/aggregation/__init__.py
preflibtools/aggregation/singlewinner.py
preflibtools/instances/__init__.py
preflibtools/instances/convert.py
preflibtools/instances/dataset.py
preflibtools/instances/sampling.py
preflibtools/instances/sanity.py
preflibtools/instances/preflibinstance/__init__.py
preflibtools/instances/preflibinstance/categorical.py
preflibtools/instances/preflibinstance/comparison.py
preflibtools/instances/preflibinstance/instance.py
preflibtools/instances/preflibinstance/matching.py
preflibtools/instances/preflibinstance/ordinal.py
preflibtools/instances/preflibinstance/utils.py
preflibtools/properties/__init__.py
preflibtools/properties/basic.py
preflibtools/properties/decorators.py
preflibtools/properties/distances.py
preflibtools/properties/pairwisecomparisons.py
preflibtools/properties/subdomains/__init__.py
preflibtools/properties/subdomains/consecutive_ones.py
preflibtools/properties/subdomains/dichotomous/__init__.py
preflibtools/properties/subdomains/dichotomous/euclidean.py
preflibtools/properties/subdomains/dichotomous/interval.py
preflibtools/properties/subdomains/dichotomous/partition.py
preflibtools/properties/subdomains/dichotomous/singlecrossing.py
preflibtools/properties/subdomains/ordinal/__init__.py
preflibtools/properties/subdomains/ordinal/euclidean.py
preflibtools/properties/subdomains/ordinal/singlecrossing.py
preflibtools/properties/subdomains/ordinal/singlepeaked/__init__.py
preflibtools/properties/subdomains/ordinal/singlepeaked/k_alternative_deletion.py
preflibtools/properties/subdomains/ordinal/singlepeaked/k_alternative_partition.py
preflibtools/properties/subdomains/ordinal/singlepeaked/k_axes.py
preflibtools/properties/subdomains/ordinal/singlepeaked/single_peaked_tree.py
preflibtools/properties/subdomains/ordinal/singlepeaked/singlepeakedness.py
preflibtools-2.0.31.dist-info/LICENSE.md
preflibtools-2.0.31.dist-info/WHEEL
preflibtools-2.0.31.dist-info/METADATA
preflibtools-2.0.31.dist-info/RECORD
