Metadata-Version: 2.3
Name: preflibtools
Version: 2.0.31
Summary: A set of tools to work with preference data from the PrefLib.org website.
Author-email: Simon Rey <reysimon@orange.fr>
Requires-Python: >=3.7
Classifier: Programming Language :: Python :: 3
Classifier: License :: OSI Approved :: GNU General Public License v3 or later (GPLv3+)
Classifier: Operating System :: OS Independent
Classifier: Programming Language :: Python :: 3.7
Classifier: Programming Language :: Python :: 3.8
Classifier: Programming Language :: Python :: 3.9
Classifier: Programming Language :: Python :: 3.10
Classifier: Programming Language :: Python :: 3.11
Classifier: Programming Language :: Python :: 3.12
Requires-Dist: numpy
Requires-Dist: mip
Requires-Dist: prefsampling>=0.1.7
Requires-Dist: coverage ; extra == "dev"
Requires-Dist: Sphinx ; extra == "dev"
Requires-Dist: sphinx_rtd_theme ; extra == "dev"
Requires-Dist: pytest ; extra == "dev"
Project-URL: Bug Tracker, https://github.com/PrefLib/preflibtools/issues
Project-URL: Homepage, https://github.com/PrefLib/preflibtools
Provides-Extra: dev
